snowav/__init__.py
snowav/cli.py
snowav/config/CoreConfig.ini
snowav/config/PointValuesCoreConfig.ini
snowav/config/__init__.py
snowav/config/config.py
snowav/config/recipes.ini
snowav/database/__init__.py
snowav/database/database.py
snowav/database/models.py
snowav/database/remove_metadata.py
snowav/database/tables.py
snowav/framework/__init__.py
snowav/framework/figures.py
snowav/framework/framework.py
snowav/framework/outputs.py
snowav/framework/point_values.py
snowav/framework/process.py
snowav/framework/process_day.py
snowav/framework/query.py
snowav/inflow/__init__.py
snowav/inflow/inflow.py
snowav/plotting/__init__.py
snowav/plotting/basin_total.py
snowav/plotting/cold_content.py
snowav/plotting/compare_runs.py
snowav/plotting/density.py
snowav/plotting/diagnostics.py
snowav/plotting/flt_image_change.py
snowav/plotting/image_change.py
snowav/plotting/inputs.py
snowav/plotting/plotlims.py
snowav/plotting/point_values.py
snowav/plotting/precip_depth.py
snowav/plotting/stn_validate.py
snowav/plotting/swe_volume.py
snowav/plotting/swi.py
snowav/plotting/write_properties.py
snowav/report/__init__.py
snowav/report/report.py
snowav/report/figs/ARS.jpg
snowav/report/figs/ASO.jpg
snowav/report/figs/CDWR.png
snowav/report/figs/FRIANT.jpg
snowav/report/figs/FRIANT.png
snowav/report/figs/JPL.jpg
snowav/report/figs/KRWA.jpg
snowav/report/figs/NRCS.jpg
snowav/report/figs/USBR.jpg
snowav/report/figs/USDA.jpg
snowav/report/figs/ars_logo.png
snowav/report/figs/changes_fig_tpl.txt
snowav/report/figs/cold_fig_tpl.txt
snowav/report/figs/diagnostics_fig_tpl.txt
snowav/report/figs/elev_fig_tpl.txt
snowav/report/figs/flt_fig_tpl.txt
snowav/report/figs/forecastchanges_fig_tpl.txt
snowav/report/figs/forecastpdep_fig_tpl.txt
snowav/report/figs/forecastswe_fig_tpl.txt
snowav/report/figs/forecastswi_fig_tpl.txt
snowav/report/figs/forecasttotals_fig_tpl.txt
snowav/report/figs/inflow_fig_tpl.txt
snowav/report/figs/logo.png
snowav-0.11.16.dist-info/METADATA
snowav-0.11.16.dist-info/RECORD
snowav-0.11.16.dist-info/WHEEL
snowav-0.11.16.dist-info/entry_points.txt
snowav-0.11.16.dist-info/top_level.txt
