Metadata-Version: 2.1
Name: snowav
Version: 0.11.16
Summary: Snow and Water Model Analysis and Visualization 
Home-page: https://github.com/USDA-ARS-NWRC/snowav
Author: Mark Robertson
Author-email: mark.robertson@usda.gov
License: CC0 1.0
Keywords: snowav
Platform: UNKNOWN
Classifier: Development Status :: 2 - Pre-Alpha
Classifier: Intended Audience :: Developers
Classifier: Natural Language :: English
Classifier: Programming Language :: Python :: 3
Classifier: Programming Language :: Python :: 3.3
Classifier: Programming Language :: Python :: 3.4
Classifier: Programming Language :: Python :: 3.5
Requires-Dist: coloredlogs (==6.1)
Requires-Dist: cmocean (==1.1)
Requires-Dist: inicheck (<0.8,>0.7.5)
Requires-Dist: Jinja2 (==2.10.1)
Requires-Dist: latexcodec (==1.0.5)
Requires-Dist: latex (==0.7.0)
Requires-Dist: matplotlib (==2.0.0)
Requires-Dist: mysql-connector-python (==8.0.18)
Requires-Dist: pandas (==0.22.0)
Requires-Dist: netCDF4 (==1.2.9)
Requires-Dist: numpy (==1.16.3)
Requires-Dist: requests (>=2.0.0)
Requires-Dist: seaborn (==0.8)
Requires-Dist: SQLAlchemy (==1.3.3)
Requires-Dist: tablizer (<0.3.0,>=0.2.1)
Requires-Dist: urllib3 (==1.24.3)
Requires-Dist: utm (==0.4.0)
